{
  "dixon_coles": {
    "xi": 0.0012,
    "min_weight": 0.01,
    "ridge": 0.001,
    "teams": [
      "Abkhazia",
      "Afghanistan",
      "Albania",
      "Algeria",
      "American Samoa",
      "Andorra",
      "Angola",
      "Anguilla",
      "Antigua and Barbuda",
      "Argentina",
      "Armenia",
      "Aruba",
      "Australia",
      "Austria",
      "Azerbaijan",
      "Bahamas",
      "Bahrain",
      "Bangladesh",
      "Barawa",
      "Barbados",
      "Belarus",
      "Belgium",
      "Belize",
      "Benin",
      "Bermuda",
      "Bhutan",
      "Bolivia",
      "Bonaire",
      "Bosnia and Herzegovina",
      "Botswana",
      "Brazil",
      "British Virgin Islands",
      "Brunei",
      "Bulgaria",
      "Burkina Faso",
      "Burundi",
      "Cambodia",
      "Cameroon",
      "Canada",
      "Cape Verde",
      "Cayman Islands",
      "Central African Republic",
      "Chad",
      "Chile",
      "China",
      "Colombia",
      "Comoros",
      "Congo",
      "Cook Islands",
      "Costa Rica",
      "Croatia",
      "Cuba",
      "Cura\u00e7ao",
      "Cyprus",
      "Czech Republic",
      "DR Congo",
      "Denmark",
      "Djibouti",
      "Dominica",
      "Dominican Republic",
      "Ecuador",
      "Egypt",
      "El Salvador",
      "England",
      "Equatorial Guinea",
      "Estonia",
      "Eswatini",
      "Ethiopia",
      "Faroe Islands",
      "Fiji",
      "Finland",
      "France",
      "French Guiana",
      "Gabon",
      "Gambia",
      "Georgia",
      "Germany",
      "Ghana",
      "Gibraltar",
      "Greece",
      "Grenada",
      "Guadeloupe",
      "Guam",
      "Guatemala",
      "Guernsey",
      "Guinea",
      "Guinea-Bissau",
      "Guyana",
      "Haiti",
      "Honduras",
      "Hong Kong",
      "Hungary",
      "Iceland",
      "India",
      "Indonesia",
      "Iran",
      "Iraq",
      "Isle of Man",
      "Israel",
      "Italy",
      "Ivory Coast",
      "Jamaica",
      "Japan",
      "Jersey",
      "Jordan",
      "Kazakhstan",
      "Kenya",
      "Kosovo",
      "Kuwait",
      "Kyrgyzstan",
      "Laos",
      "Latvia",
      "Lebanon",
      "Lesotho",
      "Liberia",
      "Libya",
      "Liechtenstein",
      "Lithuania",
      "Luxembourg",
      "Macau",
      "Madagascar",
      "Malawi",
      "Malaysia",
      "Maldives",
      "Mali",
      "Malta",
      "Martinique",
      "Mauritania",
      "Mauritius",
      "Mexico",
      "Moldova",
      "Mongolia",
      "Montenegro",
      "Montserrat",
      "Morocco",
      "Mozambique",
      "Myanmar",
      "Namibia",
      "Nepal",
      "Netherlands",
      "New Caledonia",
      "New Zealand",
      "Nicaragua",
      "Niger",
      "Nigeria",
      "North Korea",
      "North Macedonia",
      "Northern Ireland",
      "Norway",
      "Oman",
      "Orkney",
      "Padania",
      "Pakistan",
      "Palestine",
      "Panama",
      "Papua New Guinea",
      "Paraguay",
      "Peru",
      "Philippines",
      "Poland",
      "Portugal",
      "Puerto Rico",
      "Qatar",
      "Raetia",
      "Republic of Ireland",
      "Romania",
      "Russia",
      "Rwanda",
      "Saint Kitts and Nevis",
      "Saint Lucia",
      "Saint Martin",
      "Saint Vincent and the Grenadines",
      "Samoa",
      "San Marino",
      "Saudi Arabia",
      "Scotland",
      "Senegal",
      "Serbia",
      "Seychelles",
      "Shetland",
      "Sierra Leone",
      "Singapore",
      "Sint Maarten",
      "Slovakia",
      "Slovenia",
      "Solomon Islands",
      "Somalia",
      "South Africa",
      "South Korea",
      "South Sudan",
      "Spain",
      "Sri Lanka",
      "Sudan",
      "Suriname",
      "Sweden",
      "Switzerland",
      "Syria",
      "Sz\u00e9kely Land",
      "S\u00e3o Tom\u00e9 and Pr\u00edncipe",
      "Tahiti",
      "Taiwan",
      "Tajikistan",
      "Tamil Eelam",
      "Tanzania",
      "Thailand",
      "Tibet",
      "Timor-Leste",
      "Togo",
      "Tonga",
      "Trinidad and Tobago",
      "Tunisia",
      "Turkey",
      "Turkmenistan",
      "Turks and Caicos Islands",
      "Tuvalu",
      "Uganda",
      "Ukraine",
      "United Arab Emirates",
      "United States",
      "United States Virgin Islands",
      "Uruguay",
      "Uzbekistan",
      "Vanuatu",
      "Venezuela",
      "Vietnam",
      "Wales",
      "Western Armenia",
      "Western Isles",
      "Yemen",
      "Ynys M\u00f4n",
      "Zambia",
      "Zimbabwe"
    ],
    "attack_params": {
      "Abkhazia": 1.005518791142768,
      "Afghanistan": 0.42526392319123,
      "Albania": 0.9459379272649378,
      "Algeria": 2.0704612440429035,
      "American Samoa": 0.4332581403718746,
      "Andorra": 0.4033280621495919,
      "Angola": 1.0947722916084734,
      "Anguilla": 0.3078684603678218,
      "Antigua and Barbuda": 0.3970338918973023,
      "Argentina": 3.114382974744113,
      "Armenia": 0.9265630286309688,
      "Aruba": 0.7471887838250846,
      "Australia": 1.7357454524713352,
      "Austria": 1.962343096997542,
      "Azerbaijan": 0.8129651988694445,
      "Bahamas": 0.4425098717016154,
      "Bahrain": 1.020242763099869,
      "Bangladesh": 0.5147128278522997,
      "Barawa": 0.9562529524702048,
      "Barbados": 0.7092784128969502,
      "Belarus": 1.1330878012999221,
      "Belgium": 2.60223104330263,
      "Belize": 0.6508035814429336,
      "Benin": 1.1178803223347455,
      "Bermuda": 0.9736206805665987,
      "Bhutan": 0.3812463800580633,
      "Bolivia": 1.2415563955245144,
      "Bonaire": 0.548790778715025,
      "Bosnia and Herzegovina": 1.2527646309562808,
      "Botswana": 0.735345921421166,
      "Brazil": 2.722711075184904,
      "British Virgin Islands": 0.5036185066448795,
      "Brunei": 0.3981979052609758,
      "Bulgaria": 1.0693344385187322,
      "Burkina Faso": 1.5683045216795701,
      "Burundi": 0.7945416035435885,
      "Cambodia": 0.680239794143454,
      "Cameroon": 1.3351582505581436,
      "Canada": 1.848702094567082,
      "Cape Verde": 1.3431359090389465,
      "Cayman Islands": 0.3998767240377799,
      "Central African Republic": 1.0269916463394526,
      "Chad": 0.6227848717287278,
      "Chile": 1.4545113807191201,
      "China": 0.9379475530431768,
      "Colombia": 2.3231939615081445,
      "Comoros": 0.9886369548221003,
      "Congo": 0.7952566228079848,
      "Cook Islands": 0.45588590164389475,
      "Costa Rica": 1.5069732572896088,
      "Croatia": 2.136714540139812,
      "Cuba": 0.745128567846391,
      "Cura\u00e7ao": 1.2061491692178008,
      "Cyprus": 0.9120980233348196,
      "Czech Republic": 1.658201938686236,
      "DR Congo": 1.3933862380766822,
      "Denmark": 2.0960712603411364,
      "Djibouti": 0.6480503975081714,
      "Dominica": 0.5247871611172864,
      "Dominican Republic": 1.1932008666506473,
      "Ecuador": 1.3725301621769153,
      "Egypt": 1.6099115082256448,
      "El Salvador": 0.6874876548543906,
      "England": 2.6143553339090935,
      "Equatorial Guinea": 0.8370209064668993,
      "Estonia": 0.8105348138405483,
      "Eswatini": 0.8177855612270407,
      "Ethiopia": 0.8958943504408103,
      "Faroe Islands": 0.7823655148573276,
      "Fiji": 0.7088778527306828,
      "Finland": 1.1006743030639154,
      "France": 2.807510731641892,
      "French Guiana": 0.8460462100694603,
      "Gabon": 1.3027551502776953,
      "Gambia": 1.4767902324525783,
      "Georgia": 1.5456846515163396,
      "Germany": 3.0159306804979193,
      "Ghana": 1.306015690992913,
      "Gibraltar": 0.5133167710911553,
      "Greece": 1.6372863802169138,
      "Grenada": 0.7017380424146065,
      "Guadeloupe": 1.0202383064200056,
      "Guam": 0.5697973217700676,
      "Guatemala": 1.2374747310917522,
      "Guernsey": 0.8434096697439273,
      "Guinea": 1.2081712157386615,
      "Guinea-Bissau": 0.6916894280552537,
      "Guyana": 1.1087130958171676,
      "Haiti": 1.6017186195089832,
      "Honduras": 1.0892007236756889,
      "Hong Kong": 0.7916471283008628,
      "Hungary": 1.4140186163199813,
      "Iceland": 1.5310046034050762,
      "India": 0.523786857727224,
      "Indonesia": 1.0524022152226855,
      "Iran": 1.8404396328889077,
      "Iraq": 1.1910543343838906,
      "Isle of Man": 1.2546533127783184,
      "Israel": 1.791986049591825,
      "Italy": 2.001202857561308,
      "Ivory Coast": 1.5924233771819527,
      "Jamaica": 1.0559776110613899,
      "Japan": 2.49357829986839,
      "Jersey": 1.489462424108808,
      "Jordan": 1.6653289660885646,
      "Kazakhstan": 0.8949067016669404,
      "Kenya": 0.9973744055567173,
      "Kosovo": 1.4451408273789237,
      "Kuwait": 0.997295436323703,
      "Kyrgyzstan": 0.9883170894121315,
      "Laos": 0.562275762255424,
      "Latvia": 0.6894871973641771,
      "Lebanon": 0.8400951771655026,
      "Lesotho": 0.7465145762675846,
      "Liberia": 0.8559020046456874,
      "Libya": 0.9995817761095296,
      "Liechtenstein": 0.30373443271038236,
      "Lithuania": 0.6632174634349602,
      "Luxembourg": 0.683765310236323,
      "Macau": 0.3373361640446378,
      "Madagascar": 1.2317026677867353,
      "Malawi": 0.7462813695302442,
      "Malaysia": 1.0156617290803238,
      "Maldives": 0.44385128157509457,
      "Mali": 1.2823424227310098,
      "Malta": 0.6999004119557865,
      "Martinique": 0.7861087276930218,
      "Mauritania": 0.7065074143429959,
      "Mauritius": 0.6027392968373703,
      "Mexico": 1.9682398227520863,
      "Moldova": 0.7496769017039084,
      "Mongolia": 0.37998950739841536,
      "Montenegro": 0.9799445690233627,
      "Montserrat": 0.6216009506796898,
      "Morocco": 2.069591836337352,
      "Mozambique": 1.118577599974124,
      "Myanmar": 0.6979600897480409,
      "Namibia": 0.7596836275878425,
      "Nepal": 0.44790038441422203,
      "Netherlands": 2.81045933282717,
      "New Caledonia": 1.0142683675384723,
      "New Zealand": 1.79321834803719,
      "Nicaragua": 0.8553815038493359,
      "Niger": 1.1887516188801066,
      "Nigeria": 1.8913657682392693,
      "North Korea": 1.0606864855404774,
      "North Macedonia": 1.0887036731148672,
      "Northern Ireland": 1.1101462770430917,
      "Norway": 2.8093376126917105,
      "Oman": 0.9358938460554683,
      "Orkney": 0.9815924710136723,
      "Padania": 1.4324172445445562,
      "Pakistan": 0.503421375800444,
      "Palestine": 0.9702689063312157,
      "Panama": 1.4979357976640524,
      "Papua New Guinea": 0.7021988023068216,
      "Paraguay": 1.355423807177494,
      "Peru": 1.0553807999201228,
      "Philippines": 0.8942376834726485,
      "Poland": 1.6469419481703962,
      "Portugal": 2.730949962611259,
      "Puerto Rico": 0.894110343466225,
      "Qatar": 1.308424640217542,
      "Raetia": 0.9794539898922656,
      "Republic of Ireland": 1.2290210561144288,
      "Romania": 1.3721712631857508,
      "Russia": 1.7273909394353768,
      "Rwanda": 0.7486984358666332,
      "Saint Kitts and Nevis": 0.7087844979204985,
      "Saint Lucia": 0.6232043885887252,
      "Saint Martin": 0.8527992081570963,
      "Saint Vincent and the Grenadines": 0.9189907676529931,
      "Samoa": 0.55274772491886,
      "San Marino": 0.38427095574049563,
      "Saudi Arabia": 1.1558892256538187,
      "Scotland": 1.5734966372490797,
      "Senegal": 2.280949365334308,
      "Serbia": 1.46150852844127,
      "Seychelles": 0.39922851210633786,
      "Shetland": 1.1601775979322562,
      "Sierra Leone": 0.9631026255609195,
      "Singapore": 0.7827473394696568,
      "Sint Maarten": 0.7802256372914168,
      "Slovakia": 1.3209862156946148,
      "Slovenia": 1.1129913265281681,
      "Solomon Islands": 0.7809938704322688,
      "Somalia": 0.49712227047028956,
      "South Africa": 1.268945915234685,
      "South Korea": 1.7855987046485933,
      "South Sudan": 0.5863925446564029,
      "Spain": 3.141671395059864,
      "Sri Lanka": 0.4199719340935577,
      "Sudan": 0.7228955692830744,
      "Suriname": 1.097667854104087,
      "Sweden": 2.0755827109350515,
      "Switzerland": 2.290638812805431,
      "Syria": 1.1501743060180694,
      "Sz\u00e9kely Land": 0.9455797647464632,
      "S\u00e3o Tom\u00e9 and Pr\u00edncipe": 0.6463671696547809,
      "Tahiti": 0.7643892972502743,
      "Taiwan": 0.7151034920350177,
      "Tajikistan": 0.9304947707398272,
      "Tamil Eelam": 1.404172762487685,
      "Tanzania": 0.7700019710544812,
      "Thailand": 1.1811396776176086,
      "Tibet": 0.8443199049350382,
      "Timor-Leste": 0.4693536473197016,
      "Togo": 0.9680094374604836,
      "Tonga": 0.5691513397588552,
      "Trinidad and Tobago": 1.0083541943488705,
      "Tunisia": 1.3686734512070555,
      "Turkey": 2.059556492467085,
      "Turkmenistan": 0.7984845467681465,
      "Turks and Caicos Islands": 0.37847735807496313,
      "Tuvalu": 0.7182295276205436,
      "Uganda": 1.0478587407539817,
      "Ukraine": 1.7295725321889166,
      "United Arab Emirates": 1.3138566080613823,
      "United States": 2.00291434836321,
      "United States Virgin Islands": 0.4100224549543904,
      "Uruguay": 1.7282677665018646,
      "Uzbekistan": 1.4072089273033432,
      "Vanuatu": 0.7370801398305198,
      "Venezuela": 1.61881063131619,
      "Vietnam": 1.038513625966521,
      "Wales": 1.4349560391077039,
      "Western Armenia": 1.0504424365846168,
      "Western Isles": 0.732807322602234,
      "Yemen": 1.1646990557343455,
      "Ynys M\u00f4n": 1.0522353473460075,
      "Zambia": 1.080752505070602,
      "Zimbabwe": 0.9717960149080881
    },
    "defense_params": {
      "Abkhazia": 1.034714326937257,
      "Afghanistan": 1.7436372550737271,
      "Albania": 0.6419547440766785,
      "Algeria": 0.6866252534531815,
      "American Samoa": 7.299797856044775,
      "Andorra": 1.238105143322293,
      "Angola": 0.727153913252205,
      "Anguilla": 4.022662409573587,
      "Antigua and Barbuda": 2.2597289358476265,
      "Argentina": 0.3881829079051478,
      "Armenia": 1.4576824697046875,
      "Aruba": 2.115667508640231,
      "Australia": 0.48059930503088916,
      "Austria": 0.659464018571307,
      "Azerbaijan": 1.2504122854600699,
      "Bahamas": 4.3707240366768385,
      "Bahrain": 0.9622905089360063,
      "Bangladesh": 1.9967918339704254,
      "Barawa": 1.1121725469397838,
      "Barbados": 2.5695922827248556,
      "Belarus": 1.1174585942946544,
      "Belgium": 0.5433918268149663,
      "Belize": 1.8489863969692655,
      "Benin": 0.9793968781602812,
      "Bermuda": 2.3401315739134003,
      "Bhutan": 3.1243194565278505,
      "Bolivia": 1.0295267402499402,
      "Bonaire": 2.3426801240336643,
      "Bosnia and Herzegovina": 0.8810445883746079,
      "Botswana": 1.158463941347357,
      "Brazil": 0.44982614343717253,
      "British Virgin Islands": 2.4256876839193326,
      "Brunei": 3.3120955776719625,
      "Bulgaria": 1.1442029198182242,
      "Burkina Faso": 0.8649088334422171,
      "Burundi": 1.1395712340978363,
      "Cambodia": 2.0494012528542966,
      "Cameroon": 0.6231762718096961,
      "Canada": 0.6054868108783258,
      "Cape Verde": 0.736134572896742,
      "Cayman Islands": 2.497423773243207,
      "Central African Republic": 1.5869444585594372,
      "Chad": 1.5329178102900547,
      "Chile": 0.7007390944644291,
      "China": 0.9526408305926385,
      "Colombia": 0.41125261117137707,
      "Comoros": 1.0372816281110893,
      "Congo": 1.4241666967819655,
      "Cook Islands": 3.0749829751442364,
      "Costa Rica": 0.8696684826214197,
      "Croatia": 0.6219927582723336,
      "Cuba": 1.4764921331275747,
      "Cura\u00e7ao": 1.1122938726420197,
      "Cyprus": 1.2934296959209761,
      "Czech Republic": 0.8338321772349532,
      "DR Congo": 0.5248477977102161,
      "Denmark": 0.5603779077304272,
      "Djibouti": 2.3268733335550187,
      "Dominica": 2.127012205477463,
      "Dominican Republic": 1.247161348031688,
      "Ecuador": 0.38298095612383104,
      "Egypt": 0.5639357207673652,
      "El Salvador": 0.961718805299037,
      "England": 0.4326168249222792,
      "Equatorial Guinea": 1.064540415021386,
      "Estonia": 1.1780079193345376,
      "Eswatini": 1.4175588029984934,
      "Ethiopia": 1.1781121239540255,
      "Faroe Islands": 0.9505405103437495,
      "Fiji": 2.000307748223495,
      "Finland": 0.8794508592746444,
      "France": 0.4134809694730208,
      "French Guiana": 1.3689389936116476,
      "Gabon": 1.2070837372212129,
      "Gambia": 1.1927397325421003,
      "Georgia": 0.8299043087656465,
      "Germany": 0.6216715085882951,
      "Ghana": 0.6670784337977324,
      "Gibraltar": 1.948347054666979,
      "Greece": 0.6352580277889437,
      "Grenada": 1.9855292859323905,
      "Guadeloupe": 1.292874051575087,
      "Guam": 3.32273352728112,
      "Guatemala": 1.0873261109356254,
      "Guernsey": 0.9623879463827893,
      "Guinea": 0.825799638109557,
      "Guinea-Bissau": 1.053730707657694,
      "Guyana": 1.584113450020884,
      "Haiti": 1.0446237137799512,
      "Honduras": 0.8544930266654713,
      "Hong Kong": 1.4110324815017328,
      "Hungary": 0.7382934198650831,
      "Iceland": 0.9742968942176664,
      "India": 1.2404993892896559,
      "Indonesia": 1.1976911602959488,
      "Iran": 0.5874854066110236,
      "Iraq": 0.8679357677325495,
      "Isle of Man": 1.1343927144788737,
      "Israel": 1.0463241331292954,
      "Italy": 0.5867528530128758,
      "Ivory Coast": 0.5215749617058869,
      "Jamaica": 0.8131856086836405,
      "Japan": 0.48717833156898466,
      "Jersey": 1.3810071923341571,
      "Jordan": 0.9080372212816441,
      "Kazakhstan": 1.0986997597396844,
      "Kenya": 1.1917789179986262,
      "Kosovo": 0.710037189443367,
      "Kuwait": 1.2986839978243852,
      "Kyrgyzstan": 1.2337896228836933,
      "Laos": 2.657051678520468,
      "Latvia": 1.191997161430924,
      "Lebanon": 0.9414490830780208,
      "Lesotho": 1.1370952291207033,
      "Liberia": 1.2066504777937144,
      "Libya": 0.8874312508944645,
      "Liechtenstein": 2.0626590430250435,
      "Lithuania": 1.1357514052958602,
      "Luxembourg": 0.9632086566231539,
      "Macau": 3.526659097218598,
      "Madagascar": 1.2197343863630274,
      "Malawi": 0.9976802028084079,
      "Malaysia": 1.2013196945804718,
      "Maldives": 2.332360436180786,
      "Mali": 0.5188874024137264,
      "Malta": 1.3255861096414823,
      "Martinique": 1.2286033356426878,
      "Mauritania": 0.87694671751285,
      "Mauritius": 1.343270542085484,
      "Mexico": 0.4732968004425552,
      "Moldova": 1.5544129171327055,
      "Mongolia": 2.3524988162466407,
      "Montenegro": 1.103964452578313,
      "Montserrat": 1.8729792275110142,
      "Morocco": 0.37500143005939607,
      "Mozambique": 1.2230947152228544,
      "Myanmar": 2.539129755020704,
      "Namibia": 1.1265269256829795,
      "Nepal": 1.7329354871704488,
      "Netherlands": 0.5611419921792666,
      "New Caledonia": 1.2007283912763278,
      "New Zealand": 0.9979349343647756,
      "Nicaragua": 1.111694752632927,
      "Niger": 1.0683577450605102,
      "Nigeria": 0.6217323647565308,
      "North Korea": 1.1201392387233506,
      "North Macedonia": 0.9189311195418333,
      "Northern Ireland": 0.7130558110666319,
      "Norway": 0.6769797054767401,
      "Oman": 0.8042615886624831,
      "Orkney": 1.4720527259398801,
      "Padania": 1.0250591913056502,
      "Pakistan": 2.122897114791894,
      "Palestine": 0.862610158266474,
      "Panama": 0.8139619829914603,
      "Papua New Guinea": 1.8946838924100993,
      "Paraguay": 0.5227498709458854,
      "Peru": 0.6203323489601379,
      "Philippines": 1.5176673154502593,
      "Poland": 0.7720977972962276,
      "Portugal": 0.46183884370179773,
      "Puerto Rico": 1.4550953052911426,
      "Qatar": 1.2167838366227182,
      "Raetia": 1.6339162898009043,
      "Republic of Ireland": 0.6600657989547141,
      "Romania": 0.7297620878314506,
      "Russia": 0.570832301285626,
      "Rwanda": 0.7661693535888502,
      "Saint Kitts and Nevis": 2.4148858483065685,
      "Saint Lucia": 2.265127874985986,
      "Saint Martin": 1.8503308175659097,
      "Saint Vincent and the Grenadines": 1.9562988394800083,
      "Samoa": 2.7549110064788493,
      "San Marino": 2.581311999439555,
      "Saudi Arabia": 0.6994223791610006,
      "Scotland": 0.6765152041549718,
      "Senegal": 0.624439020327259,
      "Serbia": 0.7260801748213832,
      "Seychelles": 3.288717752976236,
      "Shetland": 1.4897149363437223,
      "Sierra Leone": 1.1172164819922723,
      "Singapore": 1.8320417198521373,
      "Sint Maarten": 2.3976722750345516,
      "Slovakia": 0.7900914404700987,
      "Slovenia": 0.6061684884369091,
      "Solomon Islands": 2.345991112357257,
      "Somalia": 1.3843152406331878,
      "South Africa": 0.6789043793036323,
      "South Korea": 0.6393369714237739,
      "South Sudan": 1.4244458999342018,
      "Spain": 0.32651420495056177,
      "Sri Lanka": 1.684782784974022,
      "Sudan": 0.9069505516788956,
      "Suriname": 0.9283397047857253,
      "Sweden": 0.8921730222546327,
      "Switzerland": 0.5535826894894147,
      "Syria": 0.9355339200327031,
      "Sz\u00e9kely Land": 1.1478546597454096,
      "S\u00e3o Tom\u00e9 and Pr\u00edncipe": 2.330479004842157,
      "Tahiti": 1.3800580857851734,
      "Taiwan": 2.4419825096470924,
      "Tajikistan": 1.0119019695131795,
      "Tamil Eelam": 0.9875618150567134,
      "Tanzania": 0.8191427728808427,
      "Thailand": 1.070605859644891,
      "Tibet": 1.7274412350119634,
      "Timor-Leste": 3.1096314530394378,
      "Togo": 0.9296246880544649,
      "Tonga": 3.222499016606461,
      "Trinidad and Tobago": 1.3515049003960447,
      "Tunisia": 0.8088785951486333,
      "Turkey": 0.743819343232447,
      "Turkmenistan": 1.404382633146769,
      "Turks and Caicos Islands": 3.617758587791033,
      "Tuvalu": 2.8403930675832476,
      "Uganda": 1.0093024508770212,
      "Ukraine": 0.7776834557205018,
      "United Arab Emirates": 0.8198656099736028,
      "United States": 0.7327080717543325,
      "United States Virgin Islands": 3.076560225935584,
      "Uruguay": 0.46122851567558015,
      "Uzbekistan": 0.8329584550669371,
      "Vanuatu": 2.0956856828216592,
      "Venezuela": 0.7430577904683352,
      "Vietnam": 1.1014616199043639,
      "Wales": 0.75360906258576,
      "Western Armenia": 1.054013812826167,
      "Western Isles": 1.1164666825744105,
      "Yemen": 1.5655976783167227,
      "Ynys M\u00f4n": 0.8729426753276243,
      "Zambia": 0.995948523515277,
      "Zimbabwe": 0.9774157044244889
    },
    "home_advantage": 1.2872492016130028,
    "rho": -0.06150453809796788
  },
  "elo": {
    "Mexico": 2011.8204538479436,
    "South Africa": 1701.008832411136,
    "South Korea": 1815.4733118055176,
    "Czech Republic": 1686.3689632985875,
    "Canada": 1830.1477841759852,
    "Bosnia and Herzegovina": 1622.660283247302,
    "Qatar": 1510.5974570026488,
    "Switzerland": 1995.3531009941025,
    "Brazil": 2040.9053124123363,
    "Morocco": 2052.638962375508,
    "Haiti": 1636.9956039952008,
    "Scotland": 1775.8704437951894,
    "United States": 1815.53511855583,
    "Paraguay": 1873.8660048193558,
    "Australia": 1907.3519200314174,
    "Turkey": 1897.4319318273397,
    "Germany": 1942.8209965944734,
    "Cura\u00e7ao": 1596.9962804760387,
    "Ivory Coast": 1864.932009675163,
    "Ecuador": 1942.7908231513147,
    "Netherlands": 2010.7191758665556,
    "Japan": 1955.2858593340611,
    "Sweden": 1748.72544147775,
    "Tunisia": 1614.7479340187872,
    "Belgium": 2012.9245235317233,
    "Egypt": 1874.9727848972173,
    "Iran": 1885.4218809710942,
    "New Zealand": 1625.1107866961092,
    "Spain": 2335.853006631842,
    "Cape Verde": 1700.518727476909,
    "Saudi Arabia": 1706.5783925070616,
    "Uruguay": 1872.2626371076246,
    "France": 2191.828019102181,
    "Senegal": 1851.8790001829832,
    "Iraq": 1668.3973161084507,
    "Norway": 2035.9763825618254,
    "Argentina": 2291.4623669562475,
    "Algeria": 1857.0495201397198,
    "Austria": 1847.775759159221,
    "Jordan": 1696.439236316267,
    "Portugal": 2026.9029088039363,
    "DR Congo": 1815.3813759475593,
    "Uzbekistan": 1703.182781135152,
    "Colombia": 2068.0728767724963,
    "England": 2148.6777395372765,
    "Croatia": 1892.0666744659243,
    "Ghana": 1691.6099915189216,
    "Panama": 1717.9189619198487
  },
  "meta": {
    "fitted": "2026-07-18",
    "n_played_matches": 72,
    "n_train_matches": 8025,
    "n_tournaments": 10000,
    "top_finals": [
      {
        "final": "Argentina vs Spain",
        "prob": 1.0
      }
    ]
  }
}